sentry_stack_checker.py
sentry_stack_checker-0.4.dist-info/DESCRIPTION.rst
sentry_stack_checker-0.4.dist-info/METADATA
sentry_stack_checker-0.4.dist-info/RECORD
sentry_stack_checker-0.4.dist-info/WHEEL
sentry_stack_checker-0.4.dist-info/metadata.json
sentry_stack_checker-0.4.dist-info/top_level.txt
