Metadata-Version: 2.0
Name: sentry-stack-checker
Version: 0.4
Summary: Pylint plugin for checking usage of log.exception
Home-page: https://github.com/davidszotten/sentry-stack-checker
Author: David Szotten
Author-email: davidszotten@gmail.com
License: MIT
Platform: UNKNOWN
